dicot/__init__.py
dicot/connections.py
dicot/motors.py
dicot/packets.py
dicot-0.1.0.dist-info/LICENSE
dicot-0.1.0.dist-info/WHEEL
dicot-0.1.0.dist-info/METADATA
dicot-0.1.0.dist-info/RECORD
