Metadata-Version: 2.1
Name: dicot
Version: 0.1.0
Summary: Controls Futaba Command-Type Servo motors.
Home-page: https://github.com/lanius/dicot
License: MIT
Author: lanius
Author-email: lanius@nirvake.org
Requires-Python: >=3.6,<4.0
Classifier: License :: OSI Approved :: MIT License
Classifier: Programming Language :: Python :: 3
Classifier: Programming Language :: Python :: 3.6
Classifier: Programming Language :: Python :: 3.7
Classifier: Programming Language :: Python :: 3.8
Requires-Dist: pyserial
Project-URL: Repository, https://github.com/lanius/dicot
